vertere/__init__.py
vertere/git_repository.py
vertere/incrementer.py
vertere/promoter_config.py
vertere/version.py
vertere/version_parser.py
vertere/version_postfix.py
vertere/version_postfix_loader.py
vertere/version_postfix_parser.py
vertere/version_promoter.py
vertere/version_service.py
vertere/version_storage.py
vertere/vertere.py
vertere/data/postfix_config.json
vertere-1.1.0.dist-info/LICENSE
vertere-1.1.0.dist-info/METADATA
vertere-1.1.0.dist-info/WHEEL
vertere-1.1.0.dist-info/entry_points.txt
vertere-1.1.0.dist-info/top_level.txt
vertere-1.1.0.dist-info/RECORD
