Metadata-Version: 2.1
Name: vertere
Version: 1.1.0
Summary: Vertere is a simple semantic versioning cli program that uses git tags for persisting
Home-page: https://github.com/mulecode/vertere
Author: Rafael Mule
Author-email: rafael@mulecode.co.uk
License: MIT
Classifier: Programming Language :: Python :: 3
Classifier: License :: OSI Approved :: GNU General Public License v3 (GPLv3)
Classifier: Operating System :: OS Independent
Requires-Python: >=3.9
License-File: LICENSE
Requires-Dist: click ==8.1.7
Requires-Dist: GitPython ==3.1.41
Requires-Dist: PyYAML ==6.0.1
